idx_flow/__init__.py
idx_flow/layers.py
idx_flow/py.typed
idx_flow/utils.py
idx_flow-0.1.0.dist-info/licenses/LICENSE
idx_flow-0.1.0.dist-info/METADATA
idx_flow-0.1.0.dist-info/WHEEL
idx_flow-0.1.0.dist-info/top_level.txt
idx_flow-0.1.0.dist-info/RECORD
