Metadata-Version: 2.4
Name: idx-flow
Version: 0.1.0
Summary: Index-based spherical convolutions for HEALPix grids in PyTorch
Author-email: Otavio Medeiros Feitosa <otavio.feitosa@inpe.br>
Maintainer-email: Otavio Medeiros Feitosa <otavio.feitosa@inpe.br>
License: MIT
Project-URL: Homepage, https://github.com/otavio-feitosa/idx-flow
Project-URL: Documentation, https://github.com/otavio-feitosa/idx-flow#readme
Project-URL: Repository, https://github.com/otavio-feitosa/idx-flow
Project-URL: Issues, https://github.com/otavio-feitosa/idx-flow/issues
Keywords: deep-learning,pytorch,spherical-convolution,healpix,atmospheric-science,geometric-deep-learning,neural-networks,climate-data,GAN,encoder-decoder
Classifier: Development Status :: 4 - Beta
Classifier: Intended Audience :: Science/Research
Classifier: Intended Audience :: Developers
Classifier: License :: OSI Approved :: MIT License
Classifier: Operating System :: OS Independent
Classifier: Programming Language :: Python :: 3
Classifier: Programming Language :: Python :: 3.8
Classifier: Programming Language :: Python :: 3.9
Classifier: Programming Language :: Python :: 3.10
Classifier: Programming Language :: Python :: 3.11
Classifier: Programming Language :: Python :: 3.12
Classifier: Topic :: Scientific/Engineering
Classifier: Topic :: Scientific/Engineering :: Artificial Intelligence
Classifier: Topic :: Scientific/Engineering :: Atmospheric Science
Classifier: Topic :: Scientific/Engineering :: Physics
Requires-Python: >=3.8
License-File: LICENSE
Requires-Dist: torch>=1.9.0
Requires-Dist: numpy>=1.19.0
Requires-Dist: healpy>=1.15.0
Requires-Dist: scikit-learn>=0.24.0
Provides-Extra: dev
Requires-Dist: pytest>=7.0.0; extra == "dev"
Requires-Dist: pytest-cov>=4.0.0; extra == "dev"
Requires-Dist: black>=23.0.0; extra == "dev"
Requires-Dist: isort>=5.12.0; extra == "dev"
Requires-Dist: mypy>=1.0.0; extra == "dev"
Requires-Dist: flake8>=6.0.0; extra == "dev"
Provides-Extra: docs
Requires-Dist: sphinx>=6.0.0; extra == "docs"
Requires-Dist: sphinx-rtd-theme>=1.2.0; extra == "docs"
Requires-Dist: myst-parser>=1.0.0; extra == "docs"
Dynamic: license-file
